odin_sdk/__init__.py
odin_sdk/api_client.py
odin_sdk/api_response.py
odin_sdk/configuration.py
odin_sdk/exceptions.py
odin_sdk/py.typed
odin_sdk/rest.py
odin_sdk/api/__init__.py
odin_sdk/api/actions_api.py
odin_sdk/api/agents_api.py
odin_sdk/api/chat_api.py
odin_sdk/api/custom_tools_api.py
odin_sdk/api/data_types_api.py
odin_sdk/api/default_api.py
odin_sdk/api/execution_history_api.py
odin_sdk/api/jsons_api.py
odin_sdk/api/knowledge_base_api.py
odin_sdk/api/projects_api.py
odin_sdk/api/roles_api.py
odin_sdk/api/schedule_management_api.py
odin_sdk/api/tools_api.py
odin_sdk/models/__init__.py
odin_sdk/models/actions_rules.py
odin_sdk/models/activate_custom_agent_response.py
odin_sdk/models/add_members_rules.py
odin_sdk/models/add_user_to_project_request.py
odin_sdk/models/add_user_to_project_response.py
odin_sdk/models/agents_rules.py
odin_sdk/models/ai_classify_request.py
odin_sdk/models/ai_classify_response.py
odin_sdk/models/ai_summarize_request.py
odin_sdk/models/ai_summarize_response.py
odin_sdk/models/analytics_rules.py
odin_sdk/models/api_key.py
odin_sdk/models/api_tool_request.py
odin_sdk/models/api_tool_response.py
odin_sdk/models/assistant_rules.py
odin_sdk/models/batch_delete_request.py
odin_sdk/models/batch_delete_response.py
odin_sdk/models/blog.py
odin_sdk/models/blog_regenerate_request.py
odin_sdk/models/blog_regenerate_response.py
odin_sdk/models/blog_regenerate_section_request.py
odin_sdk/models/blog_regenerate_section_response.py
odin_sdk/models/blog_request.py
odin_sdk/models/blog_response.py
odin_sdk/models/blog_section.py
odin_sdk/models/body_find_prospeo_data_tools_prospeo_post.py
odin_sdk/models/category_input.py
odin_sdk/models/chat_model_info_response.py
odin_sdk/models/chat_rules.py
odin_sdk/models/clone_public_tool_request.py
odin_sdk/models/compute_column_async_response.py
odin_sdk/models/compute_column_cancel_response.py
odin_sdk/models/compute_column_jobs_response.py
odin_sdk/models/compute_column_request.py
odinai_sdk-3.0.111.dist-info/METADATA
odinai_sdk-3.0.111.dist-info/WHEEL
odinai_sdk-3.0.111.dist-info/top_level.txt
odinai_sdk-3.0.111.dist-info/RECORD
