Metadata-Version: 2.4
Name: odinai-sdk
Version: 3.0.111
Summary: Odin AI Python SDK - Official Python client library for Odin AI API
Home-page: https://getodin.ai
Author: Odin AI Team
Author-email: Odin AI Team <support@getodin.ai>
License: MIT
Project-URL: Repository, https://github.com/getodin/odin-sdk
Project-URL: Homepage, https://getodin.ai
Keywords: odin,ai,api,sdk,python,cybersecurity,security
Requires-Python: >=3.9
Requires-Dist: urllib3<3.0.0,>=2.1.0
Requires-Dist: python-dateutil>=2.8.2
Requires-Dist: pydantic>=2
Requires-Dist: typing-extensions>=4.7.1
Dynamic: author
Dynamic: home-page
